sortable_listview/__init__.py
sortable_listview/views.py
sortable_listview/static/sortable_listview/bootstrap.min.css
sortable_listview/templates/sortable_listview/pagination.html
sortable_listview/templates/sortable_listview/sort_links.html
django_sortable_listview-0.43.dist-info/LICENSE.txt
django_sortable_listview-0.43.dist-info/METADATA
django_sortable_listview-0.43.dist-info/WHEEL
django_sortable_listview-0.43.dist-info/top_level.txt
django_sortable_listview-0.43.dist-info/RECORD
